agnflow/__init__.py
agnflow/_core.py
agnflow/type.py
agnflow/agent/__init__.py
agnflow/agent/agents.py
agnflow/agent/hitl.py
agnflow/agent/llm.py
agnflow/agent/mcp.py
agnflow/agent/memory.py
agnflow/agent/react.py
agnflow/agent/utils.py
agnflow/core/__init__.py
agnflow/core/connection.py
agnflow/core/flow.py
agnflow/core/node.py
agnflow/core/utils.py
agnflow-0.1.4.dist-info/METADATA
agnflow-0.1.4.dist-info/WHEEL
agnflow-0.1.4.dist-info/licenses/LICENSE
agnflow-0.1.4.dist-info/RECORD
