Metadata-Version: 2.4
Name: agnflow
Version: 0.1.4
Summary: 一个简洁的 Python 智能体工作流引擎，支持同步与异步节点、分支、循环、流程图渲染。
Project-URL: Homepage, https://github.com/jianduo1/agnflow
Project-URL: Documentation, https://github.com/jianduo1/agnflow/tree/main/docs
Project-URL: Repository, https://github.com/jianduo1/agnflow.git
Project-URL: Issues, https://github.com/jianduo1/agnflow/issues
Project-URL: Changelog, https://github.com/jianduo1/agnflow/releases
Author-email: jianduo1 <jianduo1@gmail.com>
License-File: LICENSE
Keywords: agent,async,automation,llm,python,workflow
Classifier: Development Status :: 4 - Beta
Classifier: Intended Audience :: Developers
Classifier: License :: OSI Approved :: MIT License
Classifier: Operating System :: OS Independent
Classifier: Programming Language :: Python :: 3
Classifier: Programming Language :: Python :: 3.8
Classifier: Programming Language :: Python :: 3.9
Classifier: Programming Language :: Python :: 3.10
Classifier: Programming Language :: Python :: 3.11
Classifier: Programming Language :: Python :: 3.12
Classifier: Topic :: Software Development :: Libraries :: Python Modules
Classifier: Topic :: System :: Distributed Computing
Requires-Python: >=3.8
Requires-Dist: duckduckgo-search>=4.0.0
Requires-Dist: numpy>=1.21.0
Requires-Dist: openai>=1.0.0
Requires-Dist: python-dotenv>=0.19.0
Requires-Dist: pyyaml>=6.0
Requires-Dist: requests>=2.25.0
Requires-Dist: scikit-learn>=1.7.0
